supahost/__init__.py
supahost-0.0.1.dist-info/METADATA
supahost-0.0.1.dist-info/WHEEL
supahost-0.0.1.dist-info/top_level.txt
supahost-0.0.1.dist-info/RECORD
