Metadata-Version: 2.4
Name: supahost
Version: 0.0.1
Summary: Coming soon! Manage self-hosted Supabase projects
Author-email: Aaron Guerrero <aaronbguerrero@gmail.com>
License-Expression: MIT
Requires-Python: >=3.7
